README.md
requirements.txt
setup.cfg
setup.py
pcf8574/__init__.py
pcf8574/py.typed
pcf8574.egg-info/PKG-INFO
pcf8574.egg-info/SOURCES.txt
pcf8574.egg-info/dependency_links.txt
pcf8574.egg-info/not-zip-safe
pcf8574.egg-info/requires.txt
pcf8574.egg-info/top_level.txt