Metadata-Version: 2.1
Name: pcf8574
Version: 0.1.3
Summary: Library for communication with PCF8574 IO expander over I2C
Home-page: https://github.com/flyte/pcf8574
Author: Ellis Percival
Author-email: pcf8574@failcode.co.uk
License: MIT
Platform: UNKNOWN
Classifier: Programming Language :: Python
Classifier: Intended Audience :: Developers
Classifier: License :: OSI Approved :: MIT License
Classifier: Natural Language :: English
Classifier: Operating System :: OS Independent
Classifier: Topic :: Communications
Classifier: Topic :: Home Automation
Classifier: Topic :: Software Development :: Embedded Systems
Classifier: Topic :: System :: Networking
